limitlion/__init__.py
limitlion/running_counter.lua
limitlion/running_counter.py
limitlion/running_counter_get.lua
limitlion/throttle.lua
limitlion/throttle.py
limitlion-0.9.2.dist-info/LICENSE
limitlion-0.9.2.dist-info/METADATA
limitlion-0.9.2.dist-info/WHEEL
limitlion-0.9.2.dist-info/top_level.txt
limitlion-0.9.2.dist-info/RECORD
