Metadata-Version: 2.1
Name: limitlion
Version: 0.9.2
Summary: Close LimitLion
Home-page: http://github.com/closeio/limitlion
License: UNKNOWN
Platform: any
Classifier: Intended Audience :: Developers
Classifier: License :: OSI Approved :: MIT License
Classifier: Operating System :: OS Independent
Classifier: Programming Language :: Python :: 2.7
Classifier: Programming Language :: Python :: 3
Classifier: Programming Language :: Python :: 3.5
Classifier: Programming Language :: Python :: 3.6
Classifier: Topic :: Software Development :: Libraries :: Python Modules
Requires-Dist: redis (==2.10.6)
